twlog/BasicConfig.py
twlog/Code.py
twlog/LogRecord.py
twlog/__init__.py
twlog/__main__.py
twlog/Filters/__init__.py
twlog/Formatters/ANSI.py
twlog/Formatters/Rich.py
twlog/Formatters/__init__.py
twlog/Handlers/ANSI.py
twlog/Handlers/File.py
twlog/Handlers/Rich.py
twlog/Handlers/Stream.py
twlog/Handlers/__init__.py
twlog/Handlers/ChatGPT/SysLog.py
twlog/Handlers/ChatGPT/__init__.py
twlog/util/ANSIColor.py
twlog/util/Simple.py
twlog/util/__init__.py
twlog-0.70.0.dist-info/licenses/LICENSE
twlog-0.70.0.dist-info/licenses/LICENSE.GPLv3
twlog-0.70.0.dist-info/licenses/LICENSE.RPTv1
twlog-0.70.0.dist-info/METADATA
twlog-0.70.0.dist-info/WHEEL
twlog-0.70.0.dist-info/top_level.txt
twlog-0.70.0.dist-info/zip-safe
twlog-0.70.0.dist-info/RECORD
