Metadata-Version: 2.4
Name: twlog
Version: 0.70.0
Summary: Compatibility for Logging with Easy and Simple
Author: Twinkle Computing
Author-email: Twinkle Computing <twinkle@twinkle.work>
License-Expression: GPL-3.0-or-later AND LicenseRef-ResistPsychiatricTerror-1.0-or-later
Project-URL: Homepage, https://github.com/ScrapWareORG/twlog
Project-URL: Issues, https://github.com/ScrapWareORG/twlog/issues
Classifier: Operating System :: OS Independent
Requires-Python: >=3.9
License-File: LICENSE
License-File: LICENSE.GPLv3
License-File: LICENSE.RPTv1
Dynamic: license-file
